fastpreprocess/__init__.py
fastpreprocess/essential.py
fastpreprocess/fastwork.py
fastpreprocess/fw1.py
fastpreprocess/operation.py
fastpreprocess/process.py
fastpreprocess/static/1479.gif
fastpreprocess/static/FP_processed.csv
fastpreprocess/static/arrow-up-circle-fill.svg
fastpreprocess/static/car_sample.csv
fastpreprocess/static/cover.png
fastpreprocess/static/essential_chart.js
fastpreprocess/static/logo.png
fastpreprocess/static/main.js
fastpreprocess/static/menu-outline.svg
fastpreprocess/static/style.css
fastpreprocess/template/Fastprocess.html
fastpreprocess/template/Index.html
fastpreprocess/template/ViewNewDataset.html
fastpreprocess/template/action_center.html
fastpreprocess/template/dup.html
fastpreprocess/template/error_file.html
fastpreprocess/template/layout.html
fastpreprocess/template/log.html
fastpreprocess/template/testing.html
fastpreprocess-0.2.2.dist-info/METADATA
fastpreprocess-0.2.2.dist-info/WHEEL
fastpreprocess-0.2.2.dist-info/entry_points.txt
fastpreprocess-0.2.2.dist-info/top_level.txt
fastpreprocess-0.2.2.dist-info/RECORD
