Metadata-Version: 2.1
Name: fastpreprocess
Version: 0.2.2
Summary: A new way to preprocess data for ML.
Home-page: UNKNOWN
Author: Lal Krishna Arjun
Author-email: lk.arjun@hotmail.com
License: UNKNOWN
Project-URL: Source Code, https://github.com/lkarjun/fastpreprocess
Platform: UNKNOWN
Classifier: Programming Language :: Python :: 3.7
Classifier: License :: OSI Approved :: MIT License
Classifier: Operating System :: OS Independent
Classifier: Development Status :: 4 - Beta
Requires-Python: >=3.7
Requires-Dist: uvicorn (==0.13.4)
Requires-Dist: pydantic (==1.8.2)
Requires-Dist: numpy (==1.20.3)
Requires-Dist: python-multipart
Requires-Dist: fastapi (==0.65.1)
Requires-Dist: pandas (==1.2.4)
Requires-Dist: tqdm (==4.60.0)
Requires-Dist: jinja2 (==2.11.3)
Requires-Dist: pyngrok (==5.0.5)
Requires-Dist: nest-asyncio (==1.5.1)
Requires-Dist: aiofiles (==0.7.0)
Requires-Dist: httptools (==0.2.0)
